Workbook
Name Slicer_Category: #N/A
Name Slicer_Region: #N/A
Name Slicer_Segment: #N/A
Name Slicer_Ship_Mode: #N/A
Name Timeline_Order_Date: #N/A

Sheet Charts
AA1: Row Labels | AB1: Total Sales
AA2: California | AB2: =IFERROR(GETPIVOTDATA("[Measures].[Total Sales]",Analysis!$I$43,"[Location Dimension].[State]","[Location Dimension].[State].&["&AA2&"]"),0) -> 457687.63
AA3: New York | AB3: =IFERROR(GETPIVOTDATA("[Measures].[Total Sales]",Analysis!$I$43,"[Location Dimension].[State]","[Location Dimension].[State].&["&AA3&"]"),0) -> 310876.27
AA4: Texas | AB4: =IFERROR(GETPIVOTDATA("[Measures].[Total Sales]",Analysis!$I$43,"[Location Dimension].[State]","[Location Dimension].[State].&["&AA4&"]"),0) -> 170188.05
AA5: Washington | AB5: =IFERROR(GETPIVOTDATA("[Measures].[Total Sales]",Analysis!$I$43,"[Location Dimension].[State]","[Location Dimension].[State].&["&AA5&"]"),0) -> 138641.27
AA6: Pennsylvania | AB6: =IFERROR(GETPIVOTDATA("[Measures].[Total Sales]",Analysis!$I$43,"[Location Dimension].[State]","[Location Dimension].[State].&["&AA6&"]"),0) -> 116511.91
AA7: Florida | AB7: =IFERROR(GETPIVOTDATA("[Measures].[Total Sales]",Analysis!$I$43,"[Location Dimension].[State]","[Location Dimension].[State].&["&AA7&"]"),0) -> 89473.708
AA8: Illinois | AB8: =IFERROR(GETPIVOTDATA("[Measures].[Total Sales]",Analysis!$I$43,"[Location Dimension].[State]","[Location Dimension].[State].&["&AA8&"]"),0) -> 80166.101
AA9: Ohio | AB9: =IFERROR(GETPIVOTDATA("[Measures].[Total Sales]",Analysis!$I$43,"[Location Dimension].[State]","[Location Dimension].[State].&["&AA9&"]"),0) -> 78258.136
AA10: Michigan | AB10: =IFERROR(GETPIVOTDATA("[Measures].[Total Sales]",Analysis!$I$43,"[Location Dimension].[State]","[Location Dimension].[State].&["&AA10&"]"),0) -> 76269.614
AA11: Virginia | AB11: =IFERROR(GETPIVOTDATA("[Measures].[Total Sales]",Analysis!$I$43,"[Location Dimension].[State]","[Location Dimension].[State].&["&AA11&"]"),0) -> 70636.72
AA12: North Carolina | AB12: =IFERROR(GETPIVOTDATA("[Measures].[Total Sales]",Analysis!$I$43,"[Location Dimension].[State]","[Location Dimension].[State].&["&AA12&"]"),0) -> 55603.164
AA13: Indiana | AB13: =IFERROR(GETPIVOTDATA("[Measures].[Total Sales]",Analysis!$I$43,"[Location Dimension].[State]","[Location Dimension].[State].&["&AA13&"]"),0) -> 53555.36
... AA50: North Dakota | AB50: =IFERROR(GETPIVOTDATA("[Measures].[Total Sales]",Analysis!$I$43,"[Location Dimension].[State]","[Location Dimension].[State].&["&AA50&"]"),0) -> 919.91

Sheet Analysis
A1: Retail Sales Analysis
A6: Total Sales | C6: Total Profit | E6: How have Sales and Profit changed over time? | I6: Which regions generate the highest sales and profit?
A7: 2297200.9 | C7: 286397.02 | E7: Row Labels | F7: Total Sales | G7: Total Profit | I7: Row Labels | J7: Total Sales
E8: 2014 | F8: 484247.5 | G8: 49543.974 | I8: Central | J8: 501239.89
A9: Profit Margin | C9: Total Customers | E9: 2015 | F9: 470532.51 | G9: 61618.604 | I9: East | J9: 678781.24
A10: 0.12467217 | C10: 793 | E10: 2016 | F10: 609205.6 | G10: 81795.174 | I10: South | J10: 391721.91
E11: 2017 | F11: 733215.26 | G11: 93439.27 | I11: West | J11: 725457.82
A12: Total Quantity | C12: Total Orders | E12: Grand Total | F12: 2297200.9 | G12: 286397.02 | I12: Grand Total | J12: 2297200.9
A13: 37873 | C13: 5009
A15: Category | B15: All | E15: Who are the top 10 customers by sales? | I15: Which customer segments contribute the most to sales and profit?
A16: How do discounts affect profitability? | E16: Row Labels | F16: Total Sales | G16: Total Profit | I16: Row Labels | J16: Total Sales
A17: Row Labels | B17: Total Profit | E17: Sean Miller | F17: 25043.05 | G17: -1980.7393 | I17: Consumer | J17: 1161401.3
A18: 0 | B18: 320987.6 | E18: Tamara Chand | F18: 19052.218 | G18: 8981.3239 | I18: Corporate | J18: 706146.37
A19: 0.1 | B19: 9029.177 | E19: Raymond Buch | F19: 15117.339 | G19: 6976.0959 | I19: Home Office | J19: 429653.15
A20: 0.15 | B20: 1418.9915 | E20: Tom Ashbrook | F20: 14595.62 | G20: 4703.7883 | I20: Grand Total | J20: 2297200.9
A21: 0.2 | B21: 90337.306 | E21: Adrian Barton | F21: 14473.571 | G21: 5444.8055
A22: 0.3 | B22: -10369.277 | E22: Ken Lonsdale | F22: 14175.229 | G22: 806.855
A23: 0.32 | B23: -2391.1377 | E23: Sanjit Chand | F23: 14142.334 | G23: 5757.4119
A24: 0.4 | B24: -23057.05 | E24: Hunter Lopez | F24: 12873.298 | G24: 5622.4292 | I24: How do shipping modes compare in sales?
A25: 0.45 | B25: -2493.1111 | E25: Sanjit Engle | F25: 12209.438 | G25: 2650.6769 | I25: Row Labels | J25: Total Sales
A26: 0.5 | B26: -20506.428 | E26: Christopher Conant | F26: 12129.072 | G26: 2177.0493 | I26: First Class | J26: 351428.42
A27: 0.6 | B27: -5944.6552 | E27: Grand Total | F27: 153811.17 | G27: 41139.697 | I27: Same Day | J27: 128363.12
A28: 0.7 | B28: -40075.357 | I28: Second Class | J28: 459193.57
A29: 0.8 | B29: -30539.039 | I29: Standard Class | J29: 1358215.7
A30: Grand Total | B30: 286397.02 | I30: Grand Total | J30: 2297200.9
A33: Which sub-categories generate the highest and lowest profit? | E33: Which months generate the highest sales and profit? | I33: Year | J33: All
A34: Row Labels | B34: Total Profit | E34: Row Labels | F34: Total Sales | G34: Total Profit | I34: How do sales vary by category and sub-category?
A35: Copiers | B35: 55617.825 | E35: 2014 | I35: Row Labels | J35: Total Sales
A36: Phones | B36: 44515.731 | E36: Jan | F36: 14236.895 | G36: 2450.1907 | I36: Furniture | J36: 741999.8
A37: Accessories | B37: 41936.636 | E37: Feb | F37: 4519.892 | G37: 862.3084 | I37: Office Supplies | J37: 719047.03
A38: Paper | B38: 34053.569 | E38: Mar | F38: 55691.009 | G38: 498.7299 | I38: Technology | J38: 836154.03
A39: Binders | B39: 30221.763 | E39: Apr | F39: 28295.345 | G39: 3488.8352 | I39: Grand Total | J39: 2297200.9
A40: Chairs | B40: 26590.166 | E40: May | F40: 23648.287 | G40: 2738.7096
A41: Storage | B41: 21278.826 | E41: Jun | F41: 34595.128 | G41: 4976.5244
A42: Appliances | B42: 18138.005 | E42: Jul | F42: 33946.393 | G42: -841.4826 | I42: Which states generate the highest and lowest profit?
A43: Furnishings | B43: 13059.144 | E43: Aug | F43: 27909.468 | G43: 5318.105 | I43: Row Labels | J43: Total Sales
A44: Envelopes | B44: 6964.1767 | E44: Sep | F44: 81777.351 | G44: 8328.0994 | I44: California | J44: 457687.63
A45: Art | B45: 6527.787 | E45: Oct | F45: 31453.393 | G45: 3448.2573 | I45: New York | J45: 310876.27
A46: Labels | B46: 5546.254 | E46: Nov | F46: 78628.717 | G46: 9292.1269 | I46: Texas | J46: 170188.05
A47: Machines | B47: 3384.7569 | E47: Dec | F47: 69545.621 | G47: 8983.5699 | I47: Washington | J47: 138641.27
A48: Fasteners | B48: 949.5182 | E48: 2015 | I48: Pennsylvania | J48: 116511.91
A49: Supplies | B49: -1189.0995 | E49: Jan | F49: 18174.076 | G49: -3281.007 | I49: Florida | J49: 89473.708
A50: Bookcases | B50: -3472.556 | E50: Feb | F50: 11951.411 | G50: 2813.8508 | I50: Illinois | J50: 80166.101
A51: Tables | B51: -17725.481 | E51: Mar | F51: 38726.252 | G51: 9732.0978 | I51: Ohio | J51: 78258.136
A52: Grand Total | B52: 286397.02 | E52: Apr | F52: 34195.209 | G52: 4187.4962 | I52: Michigan | J52: 76269.614
E53: May | F53: 30131.686 | G53: 4667.869 | I53: Virginia | J53: 70636.72
E54: Jun | F54: 24797.292 | G54: 3335.5572 | I54: North Carolina | J54: 55603.164
E55: Jul | F55: 28765.325 | G55: 3288.6483 | I55: Indiana | J55: 53555.36
E56: Aug | F56: 36898.332 | G56: 5355.8084 | I56: Georgia | J56: 49095.84
E57: Sep | F57: 64595.918 | G57: 8209.1627 | I57: Kentucky | J57: 36591.75
E58: Oct | F58: 31404.924 | G58: 2817.366 | I58: New Jersey | J58: 35764.312
E59: Nov | F59: 75972.564 | G59: 12474.788 | I59: Arizona | J59: 35282.001
E60: Dec | F60: 74919.521 | G60: 8016.9659 | I60: Wisconsin | J60: 32114.61
E61: 2016 | I61: Colorado | J61: 32108.118
E62: Jan | F62: 18542.491 | G62: 2824.8233 | I62: Tennessee | J62: 30661.873
E63: Feb | F63: 22978.815 | G63: 5004.5795 | I63: Minnesota | J63: 29863.15
E64: Mar | F64: 51715.875 | G64: 3611.968 | I64: Massachusetts | J64: 28634.434
E65: Apr | F65: 38750.039 | G65: 2977.8149 | I65: Delaware | J65: 27451.069
E66: May | F66: 56987.728 | G66: 8662.1464 | I66: Maryland | J66: 23705.523
E67: Jun | F67: 40344.534 | G67: 4750.3781 | I67: Rhode Island | J67: 22627.956
E68: Jul | F68: 39261.963 | G68: 4432.8779 | I68: Missouri | J68: 22205.15
E69: Aug | F69: 31115.374 | G69: 2062.0693 | I69: Oklahoma | J69: 19683.39
E70: Sep | F70: 73410.025 | G70: 9328.6576 | I70: Alabama | J70: 19510.64
E71: Oct | F71: 59687.745 | G71: 16243.142 | I71: Oregon | J71: 17431.15
E72: Nov | F72: 79411.966 | G72: 4011.4075 | I72: Nevada | J72: 16729.102
E73: Dec | F73: 96999.043 | G73: 17885.309 | I73: Connecticut | J73: 13384.357
E74: 2017 | I74: Arkansas | J74: 11678.13
E75: Jan | F75: 43971.374 | G75: 7140.4391 | I75: Utah | J75: 11220.056
E76: Feb | F76: 20301.133 | G76: 1613.872 | I76: Mississippi | J76: 10771.34
E77: Mar | F77: 58872.353 | G77: 14751.891 | I77: Louisiana | J77: 9217.03
E78: Apr | F78: 36521.536 | G78: 933.29 | I78: Vermont | J78: 8929.37
E79: May | F79: 44261.11 | G79: 6342.5828 | I79: South Carolina | J79: 8481.71
E80: Jun | F80: 52981.726 | G80: 8223.3357 | I80: Nebraska | J80: 7464.93
E81: Jul | F81: 45264.416 | G81: 6952.6212 | I81: New Hampshire | J81: 7292.524
E82: Aug | F82: 63120.888 | G82: 9040.9557 | I82: Montana | J82: 5589.352
E83: Sep | F83: 87866.652 | G83: 10991.556 | I83: New Mexico | J83: 4783.522
E84: Oct | F84: 77776.923 | G84: 9275.2755 | I84: Iowa | J84: 4579.76
E85: Nov | F85: 118447.82 | G85: 9690.1037 | I85: Idaho | J85: 4382.486
E86: Dec | F86: 83829.319 | G86: 8483.3468 | I86: Kansas | J86: 2914.31
E87: Grand Total | F87: 2297200.9 | G87: 286397.02 | I87: District of Columbia | J87: 2865.02
I88: Wyoming | J88: 1603.136
I89: South Dakota | J89: 1315.56
I90: Maine | J90: 1270.53
I91: West Virginia | J91: 1209.824
I92: North Dakota | J92: 919.91
I93: Grand Total | J93: 2297200.9

Sheet Overview Dashboard

Sheet Summary Dashboard
